jsurl/__init__.py
jsurl-0.1.3.dist-info/METADATA
jsurl-0.1.3.dist-info/WHEEL
jsurl-0.1.3.dist-info/licenses/LICENSE
jsurl-0.1.3.dist-info/RECORD
