Metadata-Version: 2.4
Name: jsurl
Version: 0.1.3
Summary: Javascript-like URL parser for Python
Project-URL: Homepage, https://github.com/frodo821/jsurl
Project-URL: Repository, https://github.com/frodo821/jsurl
Author-email: frodo821 <sakaic2003@gmail.com>
License: MIT License
License-File: LICENSE
Classifier: License :: OSI Approved :: MIT License
Classifier: Programming Language :: Python :: 3
Classifier: Programming Language :: Python :: 3.10
Classifier: Programming Language :: Python :: 3.11
Classifier: Programming Language :: Python :: 3.12
Classifier: Programming Language :: Python :: 3.13
Classifier: Programming Language :: Python :: 3.14
Classifier: Programming Language :: Python :: 3.15
Classifier: Topic :: Utilities
Requires-Python: >=3.10
